thu_big_data_ml/__init__.py
thu_big_data_ml/_modidx.py
thu_big_data_ml/core.py
thu_big_data_ml/help.py
thu_big_data_ml/svm.py
thu_big_data_ml/tree.py
thu_big_data_ml/big_data_analytics/__init__.py
thu_big_data_ml/big_data_analytics/anova.py
thu_big_data_ml/svm/__init__.py
thu_big_data_ml/svm/infra.py
thu_big_data_ml/svm/kernel_hpo.py
thu_big_data_ml/svm/use_lib.py
thu_big_data_ml/svm/handy_crafted/__init__.py
thu_big_data_ml/svm/handy_crafted/kernel.py
thu_big_data_ml/svm/handy_crafted/linear.py
thu_big_data_ml-0.0.2.dist-info/LICENSE
thu_big_data_ml-0.0.2.dist-info/METADATA
thu_big_data_ml-0.0.2.dist-info/WHEEL
thu_big_data_ml-0.0.2.dist-info/entry_points.txt
thu_big_data_ml-0.0.2.dist-info/top_level.txt
thu_big_data_ml-0.0.2.dist-info/RECORD
