Metadata-Version: 2.1
Name: thu_big_data_ml
Version: 0.0.2
Summary: 这是本人学习清华大学70240403-200大数据机器学习课程的开源工作，包括对往期Assignment的实现、对Lecture的笔记与理解、对即将来的Project的实现等，欢迎各位同学一起学习一起讨论，对知识取得更好的理解。
Home-page: https://github.com/Open-Book-Studio/THU-Coursework-Machine-Learning-for-Big-Data
Author: 叶璨铭
Author-email: ycm24@mails.tsinghua.edu.cn
License: Apache Software License 2.0
Keywords: nbdev jupyter notebook python
Classifier: Development Status :: 4 - Beta
Classifier: Intended Audience :: Developers
Classifier: Natural Language :: English
Classifier: Programming Language :: Python :: 3.7
Classifier: Programming Language :: Python :: 3.8
Classifier: Programming Language :: Python :: 3.9
Classifier: Programming Language :: Python :: 3.10
Classifier: Programming Language :: Python :: 3.11
Classifier: Programming Language :: Python :: 3.12
Classifier: License :: OSI Approved :: Apache Software License
Requires-Python: >=3.7
License-File: LICENSE
Requires-Dist: fastcore
Requires-Dist: pandas
Requires-Dist: matplotlib
Requires-Dist: seaborn
Requires-Dist: openpyxl
Requires-Dist: scipy
Requires-Dist: statsmodels
Requires-Dist: ipywidgets
Provides-Extra: dev
Requires-Dist: ipykernel; extra == "dev"
Requires-Dist: nbdev; extra == "dev"
Requires-Dist: ray; extra == "dev"
Requires-Dist: optuna; extra == "dev"
Requires-Dist: plotly; extra == "dev"
Requires-Dist: nbformat; extra == "dev"
Requires-Dist: scikit-posthocs; extra == "dev"
Requires-Dist: scikit-plot; extra == "dev"
Requires-Dist: mlxtend; extra == "dev"
